{
    "clubs": [
        {
            "id": "track_and_field",
            "type": "sports",
            "name": "陸上競技部",
            "englishName": "track and field",
            "catchphrase": "",
            "intro": "",
            "place": "",
            "day": [
                { "mon": "" },
                { "tue": "" },
                { "wed": "" },
                { "thu": "" },
                { "fri": "" },
                { "satAM": "" },
                { "satPM": "" },
                { "sunAM": "" },
                { "sunPM": "" },
                { "note": "" }
            ],
            "costs": {
                "clubCost": "",
                "otherCost": ""
            },
            "manager": "",
            "records": {
                "record1": {
                    "year": "2025年度",
                    "text": []
                },
                "record2": {
                    "year": "2024年度",
                    "text": []
                }
            }
        },
        {
            "id": "swimming",
            "type": "sports",
            "name": "水泳部",
            "englishName": "swimming",
            "catchphrase": "",
            "intro": "",
            "place": "",
            "day": [
                { "mon": "" },
                { "tue": "" },
                { "wed": "" },
                { "thu": "" },
                { "fri": "" },
                { "satAM": "" },
                { "satPM": "" },
                { "sunAM": "" },
                { "sunPM": "" },
                { "note": "" }
            ],
            "costs": {
                "clubCost": "",
                "otherCost": ""
            },
            "manager": "",
            "records": {
                "record1": {
                    "year": "2025年度",
                    "text": []
                },
                "record2": {
                    "year": "2024年度",
                    "text": []
                }
            }
        },
        {
            "id": "kyudo",
            "type": "sports",
            "name": "弓道部",
            "englishName": "kyudo",
            "catchphrase": "",
            "intro": "",
            "place": "",
            "day": [
                { "mon": "" },
                { "tue": "" },
                { "wed": "" },
                { "thu": "" },
                { "fri": "" },
                { "satAM": "" },
                { "satPM": "" },
                { "sunAM": "" },
                { "sunPM": "" },
                { "note": "" }
            ],
            "costs": {
                "clubCost": "",
                "otherCost": ""
            },
            "manager": "",
            "records": {
                "record1": {
                    "year": "2025年度",
                    "text": []
                },
                "record2": {
                    "year": "2024年度",
                    "text": []
                }
            }
        },
        {
            "id": "trekking",
            "type": "sports",
            "name": "トレッキング部",
            "englishName": "trekking",
            "catchphrase": "",
            "intro": "",
            "place": "",
            "day": [
                { "mon": "" },
                { "tue": "" },
                { "wed": "" },
                { "thu": "" },
                { "fri": "" },
                { "satAM": "" },
                { "satPM": "" },
                { "sunAM": "" },
                { "sunPM": "" },
                { "note": "" }
            ],
            "costs": {
                "clubCost": "",
                "otherCost": ""
            },
            "manager": "",
            "records": {
                "record1": {
                    "year": "2025年度",
                    "text": []
                },
                "record2": {
                    "year": "2024年度",
                    "text": []
                }
            }
        },
        {
            "id": "kendo",
            "type": "sports",
            "name": "剣道部",
            "englishName": "kendo",
            "catchphrase": "",
            "intro": "",
            "place": "",
            "day": [
                { "mon": "" },
                { "tue": "" },
                { "wed": "" },
                { "thu": "" },
                { "fri": "" },
                { "satAM": "" },
                { "satPM": "" },
                { "sunAM": "" },
                { "sunPM": "" },
                { "note": "" }
            ],
            "costs": {
                "clubCost": "",
                "otherCost": ""
            },
            "manager": "",
            "records": {
                "record1": {
                    "year": "2025年度",
                    "text": []
                },
                "record2": {
                    "year": "2024年度",
                    "text": []
                }
            }
        },
        {
            "id": "soccer",
            "type": "sports",
            "name": "サッカー部",
            "englishName": "soccer",
            "catchphrase": "",
            "intro": "",
            "place": "",
            "day": [
                { "mon": "" },
                { "tue": "" },
                { "wed": "" },
                { "thu": "" },
                { "fri": "" },
                { "satAM": "" },
                { "satPM": "" },
                { "sunAM": "" },
                { "sunPM": "" },
                { "note": "" }
            ],
            "costs": {
                "clubCost": "",
                "otherCost": ""
            },
            "manager": "",
            "records": {
                "record1": {
                    "year": "2025年度",
                    "text": []
                },
                "record2": {
                    "year": "2024年度",
                    "text": []
                }
            }
        },
        {
            "id": "rugby",
            "type": "sports",
            "name": "ラグビー部",
            "englishName": "rugby",
            "catchphrase": "",
            "intro": "",
            "place": "",
            "day": [
                { "mon": "" },
                { "tue": "" },
                { "wed": "" },
                { "thu": "" },
                { "fri": "" },
                { "satAM": "" },
                { "satPM": "" },
                { "sunAM": "" },
                { "sunPM": "" },
                { "note": "" }
            ],
            "costs": {
                "clubCost": "",
                "otherCost": ""
            },
            "manager": "",
            "records": {
                "record1": {
                    "year": "2025年度",
                    "text": []
                },
                "record2": {
                    "year": "2024年度",
                    "text": []
                }
            }
        },
        {
            "id": "volleyball-M",
            "type": "sports",
            "name": "男子バレーボール部",
            "englishName": "volleyball",
            "catchphrase": "",
            "intro": "",
            "place": "",
            "day": [
                { "mon": "" },
                { "tue": "" },
                { "wed": "" },
                { "thu": "" },
                { "fri": "" },
                { "satAM": "" },
                { "satPM": "" },
                { "sunAM": "" },
                { "sunPM": "" },
                { "note": "" }
            ],
            "costs": {
                "clubCost": "",
                "otherCost": ""
            },
            "manager": "",
            "records": {
                "record1": {
                    "year": "2025年度",
                    "text": []
                },
                "record2": {
                    "year": "2024年度",
                    "text": []
                }
            }
        },
        {
            "id": "volleyball-F",
            "type": "sports",
            "name": "女子バレーボール部",
            "englishName": "volleyball",
            "catchphrase": "",
            "intro": "",
            "place": "",
            "day": [
                { "mon": "" },
                { "tue": "" },
                { "wed": "" },
                { "thu": "" },
                { "fri": "" },
                { "satAM": "" },
                { "satPM": "" },
                { "sunAM": "" },
                { "sunPM": "" },
                { "note": "" }
            ],
            "costs": {
                "clubCost": "",
                "otherCost": ""
            },
            "manager": "",
            "records": {
                "record1": {
                    "year": "2025年度",
                    "text": []
                },
                "record2": {
                    "year": "2024年度",
                    "text": []
                }
            }
        },
        {
            "id": "handball-M",
            "type": "sports",
            "name": "男子ハンドボール部",
            "englishName": "handball",
            "catchphrase": "",
            "intro": "",
            "place": "",
            "day": [
                { "mon": "" },
                { "tue": "" },
                { "wed": "" },
                { "thu": "" },
                { "fri": "" },
                { "satAM": "" },
                { "satPM": "" },
                { "sunAM": "" },
                { "sunPM": "" },
                { "note": "" }
            ],
            "costs": {
                "clubCost": "",
                "otherCost": ""
            },
            "manager": "",
            "records": {
                "record1": {
                    "year": "2025年度",
                    "text": []
                },
                "record2": {
                    "year": "2024年度",
                    "text": []
                }
            }
        },
        {
            "id": "handball-F",
            "type": "sports",
            "name": "女子ハンドボール部",
            "englishName": "handball",
            "catchphrase": "",
            "intro": "",
            "place": "",
            "day": [
                { "mon": "" },
                { "tue": "" },
                { "wed": "" },
                { "thu": "" },
                { "fri": "" },
                { "satAM": "" },
                { "satPM": "" },
                { "sunAM": "" },
                { "sunPM": "" },
                { "note": "" }
            ],
            "costs": {
                "clubCost": "",
                "otherCost": ""
            },
            "manager": "",
            "records": {
                "record1": {
                    "year": "2025年度",
                    "text": []
                },
                "record2": {
                    "year": "2024年度",
                    "text": []
                }
            }
        },
        {
            "id": "basketball-M",
            "type": "sports",
            "name": "男子バスケットボール部",
            "englishName": "basketball",
            "catchphrase": "",
            "intro": "",
            "place": "",
            "day": [
                { "mon": "" },
                { "tue": "" },
                { "wed": "" },
                { "thu": "" },
                { "fri": "" },
                { "satAM": "" },
                { "satPM": "" },
                { "sunAM": "" },
                { "sunPM": "" },
                { "note": "" }
            ],
            "costs": {
                "clubCost": "",
                "otherCost": ""
            },
            "manager": "",
            "records": {
                "record1": {
                    "year": "2025年度",
                    "text": []
                },
                "record2": {
                    "year": "2024年度",
                    "text": []
                }
            }
        },
        {
            "id": "basketball-F",
            "type": "sports",
            "name": "女子バスケットボール部",
            "englishName": "basketball",
            "catchphrase": "",
            "intro": "",
            "place": "",
            "day": [
                { "mon": "" },
                { "tue": "" },
                { "wed": "" },
                { "thu": "" },
                { "fri": "" },
                { "satAM": "" },
                { "satPM": "" },
                { "sunAM": "" },
                { "sunPM": "" },
                { "note": "" }
            ],
            "costs": {
                "clubCost": "",
                "otherCost": ""
            },
            "manager": "",
            "records": {
                "record1": {
                    "year": "2025年度",
                    "text": []
                },
                "record2": {
                    "year": "2024年度",
                    "text": []
                }
            }
        },
        {
            "id": "baseball",
            "type": "sports",
            "name": "野球部",
            "englishName": "baseball",
            "catchphrase": "",
            "intro": "",
            "place": "",
            "day": [
                { "mon": "" },
                { "tue": "" },
                { "wed": "" },
                { "thu": "" },
                { "fri": "" },
                { "satAM": "" },
                { "satPM": "" },
                { "sunAM": "" },
                { "sunPM": "" },
                { "note": "" }
            ],
            "costs": {
                "clubCost": "",
                "otherCost": ""
            },
            "manager": "",
            "records": {
                "record1": {
                    "year": "2025年度",
                    "text": []
                },
                "record2": {
                    "year": "2024年度",
                    "text": []
                }
            }
        },
        {
            "id": "table_tennis",
            "type": "sports",
            "name": "卓球部",
            "englishName": "table tennis",
            "catchphrase": "",
            "intro": "",
            "place": "",
            "day": [
                { "mon": "" },
                { "tue": "" },
                { "wed": "" },
                { "thu": "" },
                { "fri": "" },
                { "satAM": "" },
                { "satPM": "" },
                { "sunAM": "" },
                { "sunPM": "" },
                { "note": "" }
            ],
            "costs": {
                "clubCost": "",
                "otherCost": ""
            },
            "manager": "",
            "records": {
                "record1": {
                    "year": "2025年度",
                    "text": []
                },
                "record2": {
                    "year": "2024年度",
                    "text": []
                }
            }
        },
        {
            "id": "badminton-M",
            "type": "sports",
            "name": "男子バトミントン部",
            "englishName": "badminton",
            "catchphrase": "",
            "intro": "",
            "place": "",
            "day": [
                { "mon": "" },
                { "tue": "" },
                { "wed": "" },
                { "thu": "" },
                { "fri": "" },
                { "satAM": "" },
                { "satPM": "" },
                { "sunAM": "" },
                { "sunPM": "" },
                { "note": "" }
            ],
            "costs": {
                "clubCost": "",
                "otherCost": ""
            },
            "manager": "",
            "records": {
                "record1": {
                    "year": "2025年度",
                    "text": []
                },
                "record2": {
                    "year": "2024年度",
                    "text": []
                }
            }
        },
        {
            "id": "badminton-F",
            "type": "sports",
            "name": "女子バトミントン部",
            "englishName": "badminton",
            "catchphrase": "",
            "intro": "",
            "place": "",
            "day": [
                { "mon": "" },
                { "tue": "" },
                { "wed": "" },
                { "thu": "" },
                { "fri": "" },
                { "satAM": "" },
                { "satPM": "" },
                { "sunAM": "" },
                { "sunPM": "" },
                { "note": "" }
            ],
            "costs": {
                "clubCost": "",
                "otherCost": ""
            },
            "manager": "",
            "records": {
                "record1": {
                    "year": "2025年度",
                    "text": []
                },
                "record2": {
                    "year": "2024年度",
                    "text": []
                }
            }
        },

        {
            "id": "hard_tennis-F",
            "type": "sports",
            "name": "男子硬式テニス部",
            "englishName": "hard tennis",
            "catchphrase": "",
            "intro": "",
            "place": "",
            "day": [
                { "mon": "" },
                { "tue": "" },
                { "wed": "" },
                { "thu": "" },
                { "fri": "" },
                { "satAM": "" },
                { "satPM": "" },
                { "sunAM": "" },
                { "sunPM": "" },
                { "note": "" }
            ],
            "costs": {
                "clubCost": "",
                "otherCost": ""
            },
            "manager": "",
            "records": {
                "record1": {
                    "year": "2025年度",
                    "text": []
                },
                "record2": {
                    "year": "2024年度",
                    "text": []
                }
            }
        },
        {
            "id": "hard_tennis-M",
            "type": "sports",
            "name": "女子硬式テニス部",
            "englishName": "hard tennis",
            "catchphrase": "",
            "intro": "",
            "place": "",
            "day": [
                { "mon": "" },
                { "tue": "" },
                { "wed": "" },
                { "thu": "" },
                { "fri": "" },
                { "satAM": "" },
                { "satPM": "" },
                { "sunAM": "" },
                { "sunPM": "" },
                { "note": "" }
            ],
            "costs": {
                "clubCost": "",
                "otherCost": ""
            },
            "manager": "",
            "records": {
                "record1": {
                    "year": "2025年度",
                    "text": []
                },
                "record2": {
                    "year": "2024年度",
                    "text": []
                }
            }
        },

        {
            "id": "soft_tennis-F",
            "type": "sports",
            "name": "男子ソフトテニス部",
            "englishName": "soft tennis",
            "catchphrase": "",
            "intro": "",
            "place": "",
            "day": [
                { "mon": "" },
                { "tue": "" },
                { "wed": "" },
                { "thu": "" },
                { "fri": "" },
                { "satAM": "" },
                { "satPM": "" },
                { "sunAM": "" },
                { "sunPM": "" },
                { "note": "" }
            ],
            "costs": {
                "clubCost": "",
                "otherCost": ""
            },
            "manager": "",
            "records": {
                "record1": {
                    "year": "2025年度",
                    "text": []
                },
                "record2": {
                    "year": "2024年度",
                    "text": []
                }
            }
        },
        {
            "id": "soft_tennis-M",
            "type": "sports",
            "name": "女子ソフトテニス部",
            "englishName": "soft tennis",
            "catchphrase": "",
            "intro": "",
            "place": "",
            "day": [
                { "mon": "" },
                { "tue": "" },
                { "wed": "" },
                { "thu": "" },
                { "fri": "" },
                { "satAM": "" },
                { "satPM": "" },
                { "sunAM": "" },
                { "sunPM": "" },
                { "note": "" }
            ],
            "costs": {
                "clubCost": "",
                "otherCost": ""
            },
            "manager": "",
            "records": {
                "record1": {
                    "year": "2025年度",
                    "text": []
                },
                "record2": {
                    "year": "2024年度",
                    "text": []
                }
            }
        },
        {
            "id": "english_conversation",
            "type": "culture",
            "name": "英会話部",
            "englishName": "english conversation",
            "catchphrase": "",
            "intro": "",
            "place": "",
            "day": [
                { "mon": "" },
                { "tue": "" },
                { "wed": "" },
                { "thu": "" },
                { "fri": "" },
                { "satAM": "" },
                { "satPM": "" },
                { "sunAM": "" },
                { "sunPM": "" },
                { "note": "" }
            ],
            "costs": {
                "clubCost": "",
                "otherCost": ""
            },
            "manager": "",
            "records": {
                "record1": {
                    "year": "2025年度",
                    "text": []
                },
                "record2": {
                    "year": "2024年度",
                    "text": []
                }
            }
        },
        {
            "id": "chorus",
            "type": "culture",
            "name": "合唱部",
            "englishName": "chorus",
            "catchphrase": "",
            "intro": "",
            "place": "",
            "day": [
                { "mon": "" },
                { "tue": "" },
                { "wed": "" },
                { "thu": "" },
                { "fri": "" },
                { "satAM": "" },
                { "satPM": "" },
                { "sunAM": "" },
                { "sunPM": "" },
                { "note": "" }
            ],
            "costs": {
                "clubCost": "",
                "otherCost": ""
            },
            "manager": "",
            "records": {
                "record1": {
                    "year": "2025年度",
                    "text": []
                },
                "record2": {
                    "year": "2024年度",
                    "text": []
                }
            }
        },
        {
            "id": "SSH_chemistry",
            "type": "culture",
            "name": "SSH部化学班",
            "englishName": "SSH chemistry",
            "catchphrase": "",
            "intro": "",
            "place": "",
            "day": [
                { "mon": "" },
                { "tue": "" },
                { "wed": "" },
                { "thu": "" },
                { "fri": "" },
                { "satAM": "" },
                { "satPM": "" },
                { "sunAM": "" },
                { "sunPM": "" },
                { "note": "" }
            ],
            "costs": {
                "clubCost": "",
                "otherCost": ""
            },
            "manager": "",
            "records": {
                "record1": {
                    "year": "2025年度",
                    "text": []
                },
                "record2": {
                    "year": "2024年度",
                    "text": []
                }
            }
        },
        {
            "id": "SSH_math",
            "type": "culture",
            "name": "SSH部数学班",
            "englishName": "SSH math",
            "catchphrase": "",
            "intro": "",
            "place": "",
            "day": [
                { "mon": "" },
                { "tue": "" },
                { "wed": "" },
                { "thu": "" },
                { "fri": "" },
                { "satAM": "" },
                { "satPM": "" },
                { "sunAM": "" },
                { "sunPM": "" },
                { "note": "" }
            ],
            "costs": {
                "clubCost": "",
                "otherCost": ""
            },
            "manager": "",
            "records": {
                "record1": {
                    "year": "2025年度",
                    "text": []
                },
                "record2": {
                    "year": "2024年度",
                    "text": []
                }
            }
        },
        {
            "id": "SSH_biology",
            "type": "culture",
            "name": "SSH部生物班",
            "englishName": "SSH biology",
            "catchphrase": "",
            "intro": "",
            "place": "",
            "day": [
                { "mon": "" },
                { "tue": "" },
                { "wed": "" },
                { "thu": "" },
                { "fri": "" },
                { "satAM": "" },
                { "satPM": "" },
                { "sunAM": "" },
                { "sunPM": "" },
                { "note": "" }
            ],
            "costs": {
                "clubCost": "",
                "otherCost": ""
            },
            "manager": "",
            "records": {
                "record1": {
                    "year": "2025年度",
                    "text": []
                },
                "record2": {
                    "year": "2024年度",
                    "text": []
                }
            }
        },
        {
            "id": "SSH_physics_earthscience",
            "type": "culture",
            "name": "SSH部物理・地学班",
            "englishName": "SSH physics earthscience",
            "catchphrase": "",
            "intro": "",
            "place": "",
            "day": [
                { "mon": "" },
                { "tue": "" },
                { "wed": "" },
                { "thu": "" },
                { "fri": "" },
                { "satAM": "" },
                { "satPM": "" },
                { "sunAM": "" },
                { "sunPM": "" },
                { "note": "" }
            ],
            "costs": {
                "clubCost": "",
                "otherCost": ""
            },
            "manager": "",
            "records": {
                "record1": {
                    "year": "2025年度",
                    "text": []
                },
                "record2": {
                    "year": "2024年度",
                    "text": []
                }
            }
        },
        {
            "id": "calligraphy",
            "type": "culture",
            "name": "書道部",
            "englishName": "calligraphy",
            "catchphrase": "",
            "intro": "",
            "place": "",
            "day": [
                { "mon": "" },
                { "tue": "" },
                { "wed": "" },
                { "thu": "" },
                { "fri": "" },
                { "satAM": "" },
                { "satPM": "" },
                { "sunAM": "" },
                { "sunPM": "" },
                { "note": "" }
            ],
            "costs": {
                "clubCost": "",
                "otherCost": ""
            },
            "manager": "",
            "records": {
                "record1": {
                    "year": "2025年度",
                    "text": []
                },
                "record2": {
                    "year": "2024年度",
                    "text": []
                }
            }
        },
        {
            "id": "sakado",
            "type": "culture",
            "name": "茶華道部",
            "englishName": "sakado",
            "catchphrase": "",
            "intro": "",
            "place": "",
            "day": [
                { "mon": "" },
                { "tue": "" },
                { "wed": "" },
                { "thu": "" },
                { "fri": "" },
                { "satAM": "" },
                { "satPM": "" },
                { "sunAM": "" },
                { "sunPM": "" },
                { "note": "" }
            ],
            "costs": {
                "clubCost": "",
                "otherCost": ""
            },
            "manager": "",
            "records": {
                "record1": {
                    "year": "2025年度",
                    "text": []
                },
                "record2": {
                    "year": "2024年度",
                    "text": []
                }
            }
        },
        {
            "id": "art",
            "type": "culture",
            "name": "美術部",
            "englishName": "art",
            "catchphrase": "",
            "intro": "",
            "place": "",
            "day": [
                { "mon": "" },
                { "tue": "" },
                { "wed": "" },
                { "thu": "" },
                { "fri": "" },
                { "satAM": "" },
                { "satPM": "" },
                { "sunAM": "" },
                { "sunPM": "" },
                { "note": "" }
            ],
            "costs": {
                "clubCost": "",
                "otherCost": ""
            },
            "manager": "",
            "records": {
                "record1": {
                    "year": "2025年度",
                    "text": []
                },
                "record2": {
                    "year": "2024年度",
                    "text": []
                }
            }
        },
        {
            "id": "cartoon",
            "type": "culture",
            "name": "漫画研究部",
            "englishName": "cartoon",
            "catchphrase": "",
            "intro": "",
            "place": "",
            "day": [
                { "mon": "" },
                { "tue": "" },
                { "wed": "" },
                { "thu": "" },
                { "fri": "" },
                { "satAM": "" },
                { "satPM": "" },
                { "sunAM": "" },
                { "sunPM": "" },
                { "note": "" }
            ],
            "costs": {
                "clubCost": "",
                "otherCost": ""
            },
            "manager": "",
            "records": {
                "record1": {
                    "year": "2025年度",
                    "text": []
                },
                "record2": {
                    "year": "2024年度",
                    "text": []
                }
            }
        },
        {
            "id": "bress_band",
            "type": "culture",
            "name": "吹奏楽部",
            "englishName": "bress band",
            "catchphrase": "",
            "intro": "",
            "place": "",
            "day": [
                { "mon": "" },
                { "tue": "" },
                { "wed": "" },
                { "thu": "" },
                { "fri": "" },
                { "satAM": "" },
                { "satPM": "" },
                { "sunAM": "" },
                { "sunPM": "" },
                { "note": "" }
            ],
            "costs": {
                "clubCost": "",
                "otherCost": ""
            },
            "manager": "",
            "records": {
                "record1": {
                    "year": "2025年度",
                    "text": []
                },
                "record2": {
                    "year": "2024年度",
                    "text": []
                }
            }
        },
        {
            "id": "cooking",
            "type": "culture",
            "name": "料理部",
            "englishName": "cooking",
            "catchphrase": "",
            "intro": "",
            "place": "",
            "day": [
                { "mon": "" },
                { "tue": "" },
                { "wed": "" },
                { "thu": "" },
                { "fri": "" },
                { "satAM": "" },
                { "satPM": "" },
                { "sunAM": "" },
                { "sunPM": "" },
                { "note": "" }
            ],
            "costs": {
                "clubCost": "",
                "otherCost": ""
            },
            "manager": "",
            "records": {
                "record1": {
                    "year": "2025年度",
                    "text": []
                },
                "record2": {
                    "year": "2024年度",
                    "text": []
                }
            }
        },
        {
            "id": "shogi",
            "type": "culture",
            "name": "将棋部",
            "englishName": "shogi",
            "catchphrase": "",
            "intro": "",
            "place": "",
            "day": [
                { "mon": "" },
                { "tue": "" },
                { "wed": "" },
                { "thu": "" },
                { "fri": "" },
                { "satAM": "" },
                { "satPM": "" },
                { "sunAM": "" },
                { "sunPM": "" },
                { "note": "" }
            ],
            "costs": {
                "clubCost": "",
                "otherCost": ""
            },
            "manager": "",
            "records": {
                "record1": {
                    "year": "2025年度",
                    "text": []
                },
                "record2": {
                    "year": "2024年度",
                    "text": []
                }
            }
        },
        {
            "id": "literature",
            "type": "culture",
            "name": "文藝部",
            "englishName": "literature",
            "catchphrase": "",
            "intro": "",
            "place": "",
            "day": [
                { "mon": "" },
                { "tue": "" },
                { "wed": "" },
                { "thu": "" },
                { "fri": "" },
                { "satAM": "" },
                { "satPM": "" },
                { "sunAM": "" },
                { "sunPM": "" },
                { "note": "" }
            ],
            "costs": {
                "clubCost": "",
                "otherCost": ""
            },
            "manager": "",
            "records": {
                "record1": {
                    "year": "2025年度",
                    "text": []
                },
                "record2": {
                    "year": "2024年度",
                    "text": []
                }
            }
        },
        {
            "id": "photo",
            "type": "culture",
            "name": "写真部",
            "englishName": "photo",
            "catchphrase": "",
            "intro": "",
            "place": "",
            "day": [
                { "mon": "" },
                { "tue": "" },
                { "wed": "" },
                { "thu": "" },
                { "fri": "" },
                { "satAM": "" },
                { "satPM": "" },
                { "sunAM": "" },
                { "sunPM": "" },
                { "note": "" }
            ],
            "costs": {
                "clubCost": "",
                "otherCost": ""
            },
            "manager": "",
            "records": {
                "record1": {
                    "year": "2025年度",
                    "text": []
                },
                "record2": {
                    "year": "2024年度",
                    "text": []
                }
            }
        },
        {
            "id": "pm",
            "type": "culture",
            "name": "PM部",
            "englishName": "pm",
            "catchphrase": "",
            "intro": "",
            "place": "",
            "day": [
                { "mon": "" },
                { "tue": "" },
                { "wed": "" },
                { "thu": "" },
                { "fri": "" },
                { "satAM": "" },
                { "satPM": "" },
                { "sunAM": "" },
                { "sunPM": "" },
                { "note": "" }
            ],
            "costs": {
                "clubCost": "",
                "otherCost": ""
            },
            "manager": "",
            "records": {
                "record1": {
                    "year": "2025年度",
                    "text": []
                },
                "record2": {
                    "year": "2024年度",
                    "text": []
                }
            }
        },
        {
            "id": "library",
            "type": "special",
            "name": "図書部",
            "englishName": "library",
            "catchphrase": "",
            "intro": "",
            "place": "",
            "day": [
                { "mon": "" },
                { "tue": "" },
                { "wed": "" },
                { "thu": "" },
                { "fri": "" },
                { "satAM": "" },
                { "satPM": "" },
                { "sunAM": "" },
                { "sunPM": "" },
                { "note": "" }
            ],
            "costs": {
                "clubCost": "",
                "otherCost": ""
            },
            "manager": "",
            "records": {
                "record1": {
                    "year": "2025年度",
                    "text": []
                },
                "record2": {
                    "year": "2024年度",
                    "text": []
                }
            }
        },
        {
            "id": "broadcasting",
            "type": "special",
            "name": "放送部",
            "englishName": "broadcasting",
            "catchphrase": "",
            "intro": "",
            "place": "",
            "day": [
                { "mon": "" },
                { "tue": "" },
                { "wed": "" },
                { "thu": "" },
                { "fri": "" },
                { "satAM": "" },
                { "satPM": "" },
                { "sunAM": "" },
                { "sunPM": "" },
                { "note": "" }
            ],
            "costs": {
                "clubCost": "",
                "otherCost": ""
            },
            "manager": "",
            "records": {
                "record1": {
                    "year": "2025年度",
                    "text": []
                },
                "record2": {
                    "year": "2024年度",
                    "text": []
                }
            }
        }
    ]
}